oscrypto/__init__.py
oscrypto/_asn1.py
oscrypto/_asymmetric.py
oscrypto/_cipher_suites.py
oscrypto/_ecdsa.py
oscrypto/_errors.py
oscrypto/_ffi.py
oscrypto/_int.py
oscrypto/_pkcs1.py
oscrypto/_pkcs12.py
oscrypto/_pkcs5.py
oscrypto/_rand.py
oscrypto/_tls.py
oscrypto/_types.py
oscrypto/asymmetric.py
oscrypto/errors.py
oscrypto/kdf.py
oscrypto/keys.py
oscrypto/symmetric.py
oscrypto/tls.py
oscrypto/trust_list.py
oscrypto/util.py
oscrypto/version.py
oscrypto/_linux_bsd/__init__.py
oscrypto/_linux_bsd/trust_list.py
oscrypto/_mac/__init__.py
oscrypto/_mac/_common_crypto.py
oscrypto/_mac/_common_crypto_cffi.py
oscrypto/_mac/_common_crypto_ctypes.py
oscrypto/_mac/_core_foundation.py
oscrypto/_mac/_core_foundation_cffi.py
oscrypto/_mac/_core_foundation_ctypes.py
oscrypto/_mac/_security.py
oscrypto/_mac/_security_cffi.py
oscrypto/_mac/_security_ctypes.py
oscrypto/_mac/asymmetric.py
oscrypto/_mac/symmetric.py
oscrypto/_mac/tls.py
oscrypto/_mac/trust_list.py
oscrypto/_mac/util.py
oscrypto/_openssl/__init__.py
oscrypto/_openssl/_libcrypto.py
oscrypto/_openssl/_libcrypto_cffi.py
oscrypto/_openssl/_libcrypto_ctypes.py
oscrypto/_openssl/_libssl.py
oscrypto/_openssl/_libssl_cffi.py
oscrypto/_openssl/_libssl_ctypes.py
oscrypto/_openssl/asymmetric.py
oscrypto/_openssl/symmetric.py
oscrypto/_openssl/tls.py
oscrypto/_openssl/util.py
oscrypto/_win/__init__.py
oscrypto/_win/_advapi32.py
oscrypto/_win/_advapi32_cffi.py
oscrypto/_win/_advapi32_ctypes.py
oscrypto/_win/_cng.py
oscrypto/_win/_cng_cffi.py
oscrypto/_win/_cng_ctypes.py
oscrypto/_win/_crypt32.py
oscrypto/_win/_crypt32_cffi.py
oscrypto/_win/_crypt32_ctypes.py
oscrypto/_win/_decode.py
oscrypto/_win/_kernel32.py
oscrypto/_win/_kernel32_cffi.py
oscrypto/_win/_kernel32_ctypes.py
oscrypto/_win/_secur32.py
oscrypto/_win/_secur32_cffi.py
oscrypto/_win/_secur32_ctypes.py
oscrypto/_win/asymmetric.py
oscrypto/_win/symmetric.py
oscrypto/_win/tls.py
oscrypto/_win/trust_list.py
oscrypto/_win/util.py
elements_oscrypto-1.4.0b1.dist-info/LICENSE
elements_oscrypto-1.4.0b1.dist-info/METADATA
elements_oscrypto-1.4.0b1.dist-info/WHEEL
elements_oscrypto-1.4.0b1.dist-info/top_level.txt
elements_oscrypto-1.4.0b1.dist-info/RECORD
